emeralds/__init__.py
emeralds/cryptography/__init__.py
emeralds/cryptography/checksums.py
emeralds/tools/__init__.py
emeralds/tools/colors.py
emeralds/tools/logger.py
emeralds-0.0.40.dist-info/LICENSE.txt
emeralds-0.0.40.dist-info/METADATA
emeralds-0.0.40.dist-info/WHEEL
emeralds-0.0.40.dist-info/top_level.txt
emeralds-0.0.40.dist-info/RECORD
