Metadata-Version: 2.1
Name: emeralds
Version: 0.0.40
Summary: A testing package for learning PyPi.
Home-page: https://github.com/jasondrawdy/emeralds
Author: Jason Drawdy
Author-email: <40871836+jasondrawdy@users.noreply.github.com>
Project-URL: Documentation, https://emeralds.readthedocs.io/en/latest/
Keywords: emeralds,test,package
Classifier: Development Status :: 1 - Planning
Classifier: Intended Audience :: Developers
Classifier: License :: OSI Approved :: MIT License
Classifier: Programming Language :: Python :: 3
Classifier: Programming Language :: Python :: 3.6
Classifier: Programming Language :: Python :: 3.7
Classifier: Programming Language :: Python :: 3.8
Classifier: Programming Language :: Python :: 3.9
Classifier: Programming Language :: Python :: 3.10
Classifier: Programming Language :: Python :: 3.11
Classifier: Operating System :: OS Independent
License-File: LICENSE.txt
Provides-Extra: dev
Requires-Dist: twine ; extra == 'dev'
Requires-Dist: sphinx ; extra == 'dev'
Requires-Dist: sphinx-rtd-theme ; extra == 'dev'
Requires-Dist: sphinx-autoapi ; extra == 'dev'
